datasci_utils/__init__.py
datasci_utils/clean.py
datasci_utils/eda.py
datasci_utils/prep.py
datasci_utils-0.1.0.dist-info/METADATA
datasci_utils-0.1.0.dist-info/WHEEL
datasci_utils-0.1.0.dist-info/RECORD
